[
    {
        "image": "/images/Realisations/Aury Empire.jpg",
        "title": "Aury Empire",
        "tecno": "Illustrator",
        "subtitle": "Réalisation"
    },
    {
        "image": "/images/Realisations/Bobo's fud.png",
        "title": "Bobo's fud",
        "tecno": "Photoshop",
        "subtitle": "Réalisation"
    },
    {
        "image": "/images/Realisations/brand jj.png",
        "title": "brand jj",
        "tecno": "Illustrator",
        "subtitle": "Réalisation"
    },
    {
        "image": "/images/Realisations/burger flyer.jpg",
        "title": "burger flyer",
        "tecno": "Photoshop",
        "subtitle": "Réalisation"
    },
    {
        "image": "/images/Realisations/Christmas.png",
        "title": "Christmas",
        "tecno": "Illustrator",
        "subtitle": "Réalisation"
    },
    {
        "image": "/images/Realisations/concert.png",
        "title": "concert flyer",
        "tecno": "Photoshop",
        "subtitle": "Réalisation"
    },
    {
        "image": "/images/Realisations/dreams house.png",
        "title": "dreams house flyer",
        "tecno": "Illustrator",
        "subtitle": "Réalisation"
    },
    {
        "image": "/images/Realisations/Eteincelle.png",
        "title": "Flyer pour une musique",
        "tecno": "Photoshop",
        "subtitle": "Réalisation"
    },
    {
        "image": "/images/Realisations/fast real.png",
        "title": "flyer restaurant",
        "tecno": "Illustrator",
        "subtitle": "Réalisation"
    },
    {
        "image": "/images/Realisations/money venou.png",
        "title": "lancer son business",
        "tecno": "Photoshop",
        "subtitle": "Réalisation"
    },
    {
        "image": "/images/Realisations/Pastry.png",
        "title": "Pastry",
        "tecno": "Illustrator",
        "subtitle": "Réalisation"
    },
    {
        "image": "/images/Realisations/Paté de crab.png",
        "title": "Paté de crab",
        "tecno": "Photoshop",
        "subtitle": "Réalisation"
    },
    {
        "image": "/images/Realisations/pub valentin.png",
        "title": "pub valentin",
        "tecno": "Illustrator",
        "subtitle": "Réalisation"
    },
    {
        "image": "/images/Realisations/Valentine promo.png",
        "title": "Valentine promo",
        "tecno": "Photoshop",
        "subtitle": "Réalisation"
    }
]
